{
  "schema": "ops271_access_review_campaigns_v1",
  "source": "demo_fixture",
  "mode": "read_only",
  "product": "271ops",
  "records": [
    {
      "campaign_id": "ARC-DEMO-2026Q2-001",
      "campaign_name": "2026 Q2 Quarterly Access Review",
      "campaign_type": "Quarterly Access Review",
      "period": "2026-Q2",
      "scope": "Quarterly review for demo departments, SaaS roles, directory groups, and privileged access aliases.",
      "owner": "access-governance-owner",
      "status": "Review Open",
      "start_date": "2026-06-01",
      "due_date": "2026-06-21",
      "closed_date": null,
      "reviewer_count": 4,
      "item_count": 7,
      "completed_count": 3,
      "overdue_count": 2,
      "exception_count": 1,
      "remediation_ticket_count": 2,
      "evidence_package_ref": "EVD-271OPS-ARC-001",
      "audit_report_ref": "AUD-271OPS-ARC-001",
      "risk_level": "Medium",
      "notes": "Quarterly campaign is in progress with safe demo review metadata only."
    },
    {
      "campaign_id": "ARC-DEMO-2026Q2-002",
      "campaign_name": "2026 Q2 Privileged Admin Access Review",
      "campaign_type": "Privileged Access Review",
      "period": "2026-Q2",
      "scope": "Privileged access aliases for directory, Linux, and SaaS admin roles.",
      "owner": "privileged-access-owner",
      "status": "Overdue",
      "start_date": "2026-05-15",
      "due_date": "2026-05-31",
      "closed_date": null,
      "reviewer_count": 2,
      "item_count": 3,
      "completed_count": 1,
      "overdue_count": 2,
      "exception_count": 0,
      "remediation_ticket_count": 1,
      "evidence_package_ref": "EVD-271OPS-ARC-002",
      "audit_report_ref": null,
      "risk_level": "High",
      "notes": "Privileged review has overdue items requiring reviewer decision and remediation tracking."
    },
    {
      "campaign_id": "ARC-DEMO-2026Q2-003",
      "campaign_name": "2026 Q2 Exception Access Review",
      "campaign_type": "Exception Access Review",
      "period": "2026-Q2",
      "scope": "Temporary exception access with expiry dates before quarter close.",
      "owner": "exception-governance-owner",
      "status": "ReviewRequired",
      "start_date": "2026-06-03",
      "due_date": "2026-06-10",
      "closed_date": null,
      "reviewer_count": 2,
      "item_count": 2,
      "completed_count": 0,
      "overdue_count": 0,
      "exception_count": 2,
      "remediation_ticket_count": 0,
      "evidence_package_ref": "EVD-271OPS-ARC-003",
      "audit_report_ref": null,
      "risk_level": "High",
      "notes": "Exception review tracks expiring exception references with safe summaries only."
    },
    {
      "campaign_id": "ARC-DEMO-2026Q2-004",
      "campaign_name": "2026 Q2 Completed Evidence Campaign",
      "campaign_type": "Leaver Follow-up Review",
      "period": "2026-Q2",
      "scope": "Completed follow-up verification for demo leaver and access removal records.",
      "owner": "audit-evidence-owner",
      "status": "Completed",
      "start_date": "2026-05-20",
      "due_date": "2026-06-02",
      "closed_date": "2026-06-03",
      "reviewer_count": 2,
      "item_count": 2,
      "completed_count": 2,
      "overdue_count": 0,
      "exception_count": 0,
      "remediation_ticket_count": 1,
      "evidence_package_ref": "EVD-271OPS-ARC-004",
      "audit_report_ref": "AUD-271OPS-ARC-004",
      "risk_level": "Low",
      "notes": "Evidence package completed with safe campaign and audit report references."
    }
  ]
}
